example/ram.v
module ram #(
    parameter DEPTH = 256,
    parameter ADDR_WIDTH = 8  // log2(DEPTH)
)(
    input clk,
    input wr_en,
    input  [ADDR_WIDTH-1:0] addr,
    input  [7:0] wr_data,
    output reg [7:0] rd_data
);
    // Memory array: DEPTH locations, each 8 bits wide
    reg [7:0] mem [0:DEPTH-1];
 
    integer i;
    initial begin
        for (i = 0; i < DEPTH; i = i + 1)
            mem[i] = 8'b0;
    end
 
    always @(posedge clk) begin
        if (wr_en)
            mem[addr] <= wr_data;  // WRITE
        else
            rd_data <= mem[addr];  // READ
    end
 
endmodule

example/mac_unit.v
module mac_unit #(parameter WIDTH = 8) (
    input clk,
    input rst,
    input [WIDTH-1:0] a,
    input [WIDTH-1:0] b,
    input [2*WIDTH-1:0] acc_in,
    output reg [2*WIDTH-1:0] acc_out
);

    always @(posedge clk or posedge rst) begin
        if (rst) begin
            acc_out <= 0;
        end else begin
            acc_out <= acc_in + (a * b);
        end
    end

endmodule

template/src/register.v
// =============================================================
//  Register File  –  4 × 8-bit general-purpose registers
//  Fix: combinational read now uses blocking assignments (=)
// =============================================================
module reg_file (
    input             clk,
    input             rst,
    input             wr_en,
    input      [1:0]  rd_addr,    // destination register (write)
    input      [1:0]  rs1_addr,   // source register 1
    input      [1:0]  rs2_addr,   // source register 2
    input      [7:0]  wr_data,    // data to write
    output reg [7:0]  rs1_data,   // data out from rs1
    output reg [7:0]  rs2_data    // data out from rs2
);
    reg [7:0] regs [0:3];
    integer i;

    // Synchronous write, synchronous reset
    always @(posedge clk or posedge rst) begin
        if (rst) begin
            for (i = 0; i < 4; i = i + 1)
                regs[i] <= 8'b0;
        end else if (wr_en) begin
            regs[rd_addr] <= wr_data;
        end
    end

    // Combinational read — FIXED: use blocking assignment (=)
    always @(*) begin
        rs1_data = regs[rs1_addr];
        rs2_data = regs[rs2_addr];
    end
endmodule

example/instr_decoder.v
module instr_decoder (
    input  [7:0] instr,
    output reg [3:0] opcode,
    output reg [1:0] rd,
    output reg [1:0] rs1,
    output reg [1:0] rs2,
    output reg reg_wr_en,
    output reg ram_wr_en,
    output reg mac_en,
    output reg load_ram_en,
    output reg store_ram_en,
    output reg load_reg_en,
    output reg store_reg_en
);
    always @(*) begin
        opcode = instr[7:4];
        rd     = instr[3:2];
        rs1    = instr[3:2];
        rs2    = instr[1:0];
 
        reg_wr_en    = 0;
        ram_wr_en    = 0;
        mac_en       = 0;
        load_ram_en  = 0;
        store_ram_en = 0;
        load_reg_en  = 0;
        store_reg_en = 0;
 
        case (opcode)
            4'b0000: begin // NOP
            end
            4'b0001: begin // MAC
                mac_en    = 1;
                reg_wr_en = 1;
            end
            4'b0010: begin // LOAD_RAM: Rd = RAM[Rs2]
                load_ram_en = 1;
                reg_wr_en   = 1;
            end
            4'b0011: begin // STORE_RAM: RAM[Rs2] = Rs1
                store_ram_en = 1;
                ram_wr_en    = 1;
            end
            4'b0100: begin // LOAD_REG: Rd = Rs1
                load_reg_en = 1;
                reg_wr_en   = 1;
            end
            4'b0101: begin // STORE_REG: Rd = Rs1
                store_reg_en = 1;
                reg_wr_en    = 1;
            end
            default: begin // NOP
            end
        endcase
    end
endmodule

example/top.v
module top (
    input clk,
    input rst,
    input [7:0] instr,
    output reg [256:0] clock_count;
    // ---------- Decoder outputs ----------
    wire [3:0] opcode;
    wire [1:0] rd, rs1, rs2;
    wire reg_wr_en, ram_wr_en;
    wire mac_en, load_ram_en, store_ram_en, load_reg_en, store_reg_en;
 
    // ---------- Register File wires ----------
    wire [7:0] rs1_data, rs2_data;
    reg  [7:0] reg_wr_data;
 
    // ---------- MAC wires ----------
    wire [15:0] mac_out;
    reg  [15:0] acc_reg;
 
    // ---------- RAM wires ----------
    wire [7:0] ram_rd_data;
 
    // ===================== INSTANTIATIONS =====================
 
    instr_decoder u_decoder (
        .instr        (instr),
        .opcode       (opcode),
        .rd           (rd),
        .rs1          (rs1),
        .rs2          (rs2),
        .reg_wr_en    (reg_wr_en),
        .ram_wr_en    (ram_wr_en),
        .mac_en       (mac_en),
        .load_ram_en  (load_ram_en),
        .store_ram_en (store_ram_en),
        .load_reg_en  (load_reg_en),
        .store_reg_en (store_reg_en)
    );
 
    reg_file u_regfile (
        .clk      (clk),
        .rst      (rst),
        .wr_en    (reg_wr_en),
        .rd_addr  (rd),
        .rs1_addr (rs1),
        .rs2_addr (rs2),
        .wr_data  (reg_wr_data),
        .rs1_data (rs1_data),
        .rs2_data (rs2_data)
    );
 
    mac_unit #(.WIDTH(8)) u_mac (
        .clk     (clk),
        .rst     (rst),
        .a       (rs1_data),
        .b       (rs2_data),
        .acc_in  (acc_reg),
        .acc_out (mac_out)
    );
 
    ram #(.DEPTH(256), .ADDR_WIDTH(8)) u_ram (
        .clk     (clk),
        .wr_en   (ram_wr_en),
        .addr    ({6'b0, rs2}),
        .wr_data (rs1_data),
        .rd_data (ram_rd_data)
    );
 
    // ===================== ACCUMULATOR UPDATE =====================
    always @(posedge clk or posedge rst) begin
        if (rst)
            acc_reg <= 16'b0;
        else if (mac_en)
            acc_reg <= mac_out;
    end
 
    // ===================== WRITE-BACK MUX =====================
    always @(*) begin
        if (load_ram_en)
            reg_wr_data = ram_rd_data;       // LOAD_RAM:  Rd = RAM[Rs2]
        else if (load_reg_en || store_reg_en)
            reg_wr_data = rs1_data;          // LOAD_REG / STORE_REG: Rd = Rs1
        else if (mac_en)
            reg_wr_data = mac_out[7:0];      // MAC: lower 8 bits
        else
            reg_wr_data = 8'b0;
    end
 
endmodule

example/latency_tb/dump.vcd
$version Generated by VerilatedVcd $end
$timescale 1ps $end
 $scope module  $end
  $var wire 1 # clk $end
  $var wire 1 $ rst $end
  $var wire 8 % instr [7:0] $end
  $scope module top $end
   $var wire 1 & clk $end
   $var wire 1 ' rst $end
   $var wire 8 ( instr [7:0] $end
   $var wire 4 ) opcode [3:0] $end
   $var wire 2 * rd [1:0] $end
   $var wire 2 + rs1 [1:0] $end
   $var wire 2 , rs2 [1:0] $end
   $var wire 1 - reg_wr_en $end
   $var wire 1 . ram_wr_en $end
   $var wire 1 / mac_en $end
   $var wire 1 0 load_ram_en $end
   $var wire 1 1 store_ram_en $end
   $var wire 1 2 load_reg_en $end
   $var wire 1 3 store_reg_en $end
   $var wire 8 4 rs1_data [7:0] $end
   $var wire 8 5 rs2_data [7:0] $end
   $var wire 8 6 reg_wr_data [7:0] $end
   $var wire 16 7 mac_out [15:0] $end
   $var wire 16 8 acc_reg [15:0] $end
   $var wire 8 9 ram_rd_data [7:0] $end
   $scope module u_decoder $end
    $var wire 8 : instr [7:0] $end
    $var wire 4 ; opcode [3:0] $end
    $var wire 2 < rd [1:0] $end
    $var wire 2 = rs1 [1:0] $end
    $var wire 2 > rs2 [1:0] $end
    $var wire 1 ? reg_wr_en $end
    $var wire 1 @ ram_wr_en $end
    $var wire 1 A mac_en $end
    $var wire 1 B load_ram_en $end
    $var wire 1 C store_ram_en $end
    $var wire 1 D load_reg_en $end
    $var wire 1 E store_reg_en $end
   $upscope $end
   $scope module u_mac $end
    $var wire 32 ` WIDTH [31:0] $end
    $var wire 1 F clk $end
    $var wire 1 G rst $end
    $var wire 8 H a [7:0] $end
    $var wire 8 I b [7:0] $end
    $var wire 16 J acc_in [15:0] $end
    $var wire 16 K acc_out [15:0] $end
   $upscope $end
   $scope module u_ram $end
    $var wire 32 a DEPTH [31:0] $end
    $var wire 32 ` ADDR_WIDTH [31:0] $end
    $var wire 1 L clk $end
    $var wire 1 M wr_en $end
    $var wire 8 N addr [7:0] $end
    $var wire 8 O wr_data [7:0] $end
    $var wire 8 P rd_data [7:0] $end
    $var wire 32 Q i [31:0] $end
   $upscope $end
   $scope module u_regfile $end
    $var wire 1 R clk $end
    $var wire 1 S rst $end
    $var wire 1 T wr_en $end
    $var wire 2 U rd_addr [1:0] $end
    $var wire 2 V rs1_addr [1:0] $end
    $var wire 2 W rs2_addr [1:0] $end
    $var wire 8 X wr_data [7:0] $end
    $var wire 8 Y rs1_data [7:0] $end
    $var wire 8 Z rs2_data [7:0] $end
    $var wire 8 [ regs[0] [7:0] $end
    $var wire 8 \ regs[1] [7:0] $end
    $var wire 8 ] regs[2] [7:0] $end
    $var wire 8 ^ regs[3] [7:0] $end
    $var wire 32 _ i [31:0] $end
   $upscope $end
  $upscope $end
 $upscope $end
$enddefinitions $end


#0
1#
1$
b00000000 %
1&
1'
b00000000 (
b0000 )
b00 *
b00 +
b00 ,
0-
0.
0/
00
01
02
03
b00000000 4
b00000000 5
b00000000 6
b0000000000000000 7
b0000000000000000 8
b00000000 9
b00000000 :
b0000 ;
b00 <
b00 =
b00 >
0?
0@
0A
0B
0C
0D
0E
1F
1G
b00000000 H
b00000000 I
b0000000000000000 J
b0000000000000000 K
1L
0M
b00000000 N
b00000000 O
b00000000 P
b00000000000000000000000100000000 Q
1R
1S
0T
b00 U
b00 V
b00 W
b00000000 X
b00000000 Y
b00000000 Z
b00000000 [
b00000000 \
b00000000 ]
b00000000 ^
b00000000000000000000000000000100 _
b00000000000000000000000000001000 `
b00000000000000000000000100000000 a
#5000
0#
0&
0F
0L
0R
#10000
1#
1&
1F
1L
1R
#15000
0#
0&
0F
0L
0R
#20000
1#
1&
1F
1L
1R
#25000
0#
0&
0F
0L
0R
#30000
1#
1&
1F
1L
1R
#35000
0#
0&
0F
0L
0R
#40000
1#
0$
1&
0'
1F
0G
1L
1R
0S
#45000
0#
0&
0F
0L
0R
#50000
1#
b00000001 %
1&
b00000001 (
b01 ,
b00000001 :
b01 >
1F
1L
b00000001 N
1R
b01 W
#55000
0#
0&
0F
0L
0R
#60000
1#
1&
1F
1L
1R
#65000
0#
0&
0F
0L
0R
#70000
1#
b00000010 %
1&
b00000010 (
b10 ,
b00000010 :
b10 >
1F
1L
b00000010 N
1R
b10 W
#75000
0#
0&
0F
0L
0R
#80000
1#
1&
1F
1L
1R
#85000
0#
0&
0F
0L
0R
#90000
1#
b00000011 %
1&
b00000011 (
b11 ,
b00000011 :
b11 >
1F
1L
b00000011 N
1R
b11 W
#95000
0#
0&
0F
0L
0R
#100000
1#
1&
1F
1L
1R
#105000
0#
0&
0F
0L
0R
#110000
1#
1&
1F
1L
1R
#115000
0#
0&
0F
0L
0R
#120000
1#
1&
1F
1L
1R
#125000
0#
0&
0F
0L
0R
#130000
1#
b00000100 %
1&
b00000100 (
b01 *
b01 +
b00 ,
b00000100 :
b01 <
b01 =
b00 >
1F
1L
b00000000 N
1R
b01 U
b01 V
b00 W
#135000
0#
0&
0F
0L
0R
#140000
1#
1&
1F
1L
1R
#145000
0#
0&
0F
0L
0R
#150000
1#
1&
1F
1L
1R
#155000
0#
0&
0F
0L
0R
#160000
1#
1&
1F
1L
1R
#165000
0#
0&
0F
0L
0R
#170000
1#
1&
1F
1L
1R
#175000
0#
0&
0F
0L
0R
#180000
1#
1&
1F
1L
1R
#185000
0#
0&
0F
0L
0R
#190000
1#
b00000101 %
1&
b00000101 (
b01 ,
b00000101 :
b01 >
1F
1L
b00000001 N
1R
b01 W
#195000
0#
0&
0F
0L
0R
#200000
1#
1&
1F
1L
1R
#205000
0#
0&
0F
0L
0R
#210000
1#
1&
1F
1L
1R
#215000
0#
0&
0F
0L
0R
#220000
1#
1&
1F
1L
1R
#225000
0#
0&
0F
0L
0R
#230000
1#
1&
1F
1L
1R
#235000
0#
0&
0F
0L
0R
#240000
1#
b00000110 %
1&
b00000110 (
b10 ,
b00000110 :
b10 >
1F
1L
b00000010 N
1R
b10 W
